opnsenseapi/__about__.py
opnsenseapi/__init__.py
opnsenseapi/opnsense.py
opnsenseapi/core/__init__.py
opnsenseapi/core/core.py
opnsenseapi/core/unbound/__init__.py
opnsenseapi/core/unbound/unbound.py
opnsenseapi/core/unbound/settings/__init__.py
opnsenseapi/core/unbound/settings/host_override.py
opnsenseapi/core/unbound/settings/host_override_test.py
opnsenseapi/core/unbound/settings/settings.py
opnsenseapi/core/unbound/settings/models/__init__.py
opnsenseapi/core/unbound/settings/models/hosts.py
opnsenseapi/core/unbound/settings/models/hosts_test.py
opnsenseapi/ifaces/__init__.py
opnsenseapi/ifaces/opnsense.py
opnsenseapi-0.5.0.dist-info/METADATA
opnsenseapi-0.5.0.dist-info/WHEEL
opnsenseapi-0.5.0.dist-info/licenses/LICENSE
opnsenseapi-0.5.0.dist-info/RECORD
