Metadata-Version: 2.1
Name: opnsenseapi
Version: 0.5.0
Summary: Python API for access the opnsense api
Project-URL: Documentation, https://opnsenseapi.readthedocs.io/
Project-URL: Changelog, https://opnsenseapi.readthedocs.io/en/latest/changelog.html
Project-URL: Homepage, https://opnsenseapi.pypa.io/latest/
Project-URL: History, https://opnsenseapi.pypa.io/dev/history/opnsenseapi/
Project-URL: Tracker, https://github.com/oss4u/opnsenseapi/issues
Project-URL: Source, https://github.com/oss4u/opnsenseapi
Author-email: Marc Ende <me@sys-int.de>
License-Expression: Apache-2.0
License-File: LICENSE
Classifier: Development Status :: 4 - Beta
Classifier: License :: OSI Approved :: Apache Software License
Classifier: Programming Language :: Python :: 3 :: Only
Classifier: Programming Language :: Python :: 3.9
Classifier: Programming Language :: Python :: 3.10
Classifier: Programming Language :: Python :: 3.11
Classifier: Programming Language :: Python :: 3.12
Requires-Python: >=3.9
